pyppca/__init__.py
pyppca/pyppca.py
pyppca-0.0.3.dist-info/METADATA
pyppca-0.0.3.dist-info/RECORD
pyppca-0.0.3.dist-info/WHEEL
pyppca-0.0.3.dist-info/top_level.txt
