Metadata-Version: 2.1
Name: pyppca
Version: 0.0.3
Summary: Probabilistic PCA with Missing Values
Home-page: https://github.com/shergreen/pyppca
Author: Sheridan Green
Author-email: sheridan.green@yale.edu
License: UNKNOWN
Platform: UNKNOWN
Classifier: Programming Language :: Python :: 3
Classifier: License :: OSI Approved :: MIT License
Classifier: Operating System :: OS Independent
Requires-Dist: numpy
Requires-Dist: scipy
